daeploy/__init__.py
daeploy/communication.py
daeploy/data_types.py
daeploy/exceptions.py
daeploy/notebook.py
daeploy/testing.py
daeploy/utilities.py
daeploy/_service/__init__.py
daeploy/_service/db.py
daeploy/_service/logger.py
daeploy/_service/monitoring_api.py
daeploy/_service/service.py
daeploy/cli/__init__.py
daeploy/cli/cli.py
daeploy/cli/cliutils.py
daeploy/cli/config.py
daeploy/cli/user.py
daeploy/cli/service_template/README.md
daeploy/cli/service_template/cookiecutter.json
daeploy/cli/service_template/hooks/pre_gen_project.py
daeploy/cli/service_template/{{cookiecutter.project_name}}/.s2iignore
daeploy/cli/service_template/{{cookiecutter.project_name}}/README.md
daeploy/cli/service_template/{{cookiecutter.project_name}}/requirements.txt
daeploy/cli/service_template/{{cookiecutter.project_name}}/service.py
daeploy/cli/service_template/{{cookiecutter.project_name}}/.s2i/environment
daeploy/cli/service_template/{{cookiecutter.project_name}}/tests/base_functionality_test.py
daeploy/cli/service_template/{{cookiecutter.project_name}}/tests/user_test.py
daeploy-1.3.1.dist-info/LICENSE.txt
daeploy-1.3.1.dist-info/METADATA
daeploy-1.3.1.dist-info/WHEEL
daeploy-1.3.1.dist-info/entry_points.txt
daeploy-1.3.1.dist-info/top_level.txt
daeploy-1.3.1.dist-info/RECORD
