Metadata-Version: 2.1
Name: daeploy
Version: 1.3.1
Summary: Daeploy SDK and command-line interface
Home-page: https://daeploy.com
Author: Viking Analytics
Author-email: info@daeploy.com
License: GNU General Public License v3 (GPLv3)
Platform: UNKNOWN
Classifier: Programming Language :: Python :: 3
Classifier: Operating System :: OS Independent
Requires-Python: >=3.6
License-File: LICENSE.txt
Requires-Dist: typer
Requires-Dist: tabulate
Requires-Dist: cookiecutter
Requires-Dist: uvicorn
Requires-Dist: requests
Requires-Dist: fastapi
Requires-Dist: pydantic
Requires-Dist: numpy
Requires-Dist: setuptools
Requires-Dist: sqlalchemy
Requires-Dist: aiofiles
Requires-Dist: pytest
Requires-Dist: pandas
Requires-Dist: docker
